warpcore/__init__.py
warpcore/engineering.py
warpcore/test_engineering.py
warpcore-1.1.3.dist-info/LICENSE
warpcore-1.1.3.dist-info/METADATA
warpcore-1.1.3.dist-info/WHEEL
warpcore-1.1.3.dist-info/top_level.txt
warpcore-1.1.3.dist-info/RECORD
