Metadata-Version: 2.1
Name: warpcore
Version: 1.1.3
Summary: Streamlined multi-threaded process acceleration
Home-page: https://github.com/BlackburnHax/warpcore
Author: Brandon Blackburn
Author-email: contact@bhax.net
License: Apache 2.0
Platform: UNKNOWN
Classifier: License :: OSI Approved :: Apache Software License
Classifier: Operating System :: MacOS :: MacOS X
Classifier: Operating System :: Microsoft :: Windows
Classifier: Operating System :: POSIX
Classifier: Programming Language :: Python
Classifier: Programming Language :: Python :: 3
Classifier: Programming Language :: Python :: 3 :: Only
Classifier: Natural Language :: English
